ytpa_api_utils/__init__.py
ytpa_api_utils/constants.py
ytpa_api_utils/misc_utils.py
ytpa_api_utils/request_utils.py
ytpa_api_utils/websocket_utils.py
ytpa_api_utils-0.1.8.dist-info/METADATA
ytpa_api_utils-0.1.8.dist-info/WHEEL
ytpa_api_utils-0.1.8.dist-info/RECORD
